rostful/__init__.py
rostful/__main__.py
rostful/_version.py
rostful/client.py
rostful/config_template.py
rostful/context.py
rostful/exceptions.py
rostful/flaskapp.py
rostful/gunicorn_cfg.py
rostful/server.py
rostful/api_0_1/__init__.py
rostful/api_0_1/flask_views.py
rostful/api_0_1/index.py
rostful/api_0_2/__init__.py
rostful/frontend/__init__.py
rostful/frontend/flask_views.py
rostful/static/favicon.ico
rostful/static/js/jquery/jquery-1.11.2.js
rostful/static/js/jquery/jquery-1.11.2.min.js
rostful/static/js/jquery/jquery-1.11.2.min.map
rostful/static/js/jquery-mobile/jquery.mobile-1.4.5.css
rostful/static/js/jquery-mobile/jquery.mobile-1.4.5.js
rostful/static/js/jquery-mobile/jquery.mobile-1.4.5.min.css
rostful/static/js/jquery-mobile/jquery.mobile-1.4.5.min.js
rostful/static/js/jquery-mobile/jquery.mobile-1.4.5.min.map
rostful/static/js/jquery-mobile/jquery.mobile.icons-1.4.5.css
rostful/static/js/jquery-mobile/images/ajax-loader.gif
rostful/static/js/jquery-mobile/images/icons-png/action-black.png
rostful/static/js/jquery-mobile/images/icons-png/action-white.png
rostful/static/js/jquery-mobile/images/icons-png/alert-black.png
rostful/static/js/jquery-mobile/images/icons-png/alert-white.png
rostful/static/js/jquery-mobile/images/icons-png/arrow-d-black.png
rostful/static/js/jquery-mobile/images/icons-png/arrow-d-l-black.png
rostful/static/js/jquery-mobile/images/icons-png/arrow-d-l-white.png
rostful/static/js/jquery-mobile/images/icons-png/arrow-d-r-black.png
rostful/static/js/jquery-mobile/images/icons-png/arrow-d-r-white.png
rostful/static/js/jquery-mobile/images/icons-png/arrow-d-white.png
rostful/static/js/jquery-mobile/images/icons-png/arrow-l-black.png
rostful/static/js/jquery-mobile/images/icons-png/arrow-l-white.png
rostful/static/js/jquery-mobile/images/icons-png/arrow-r-black.png
rostful/static/js/jquery-mobile/images/icons-png/arrow-r-white.png
rostful/static/js/jquery-mobile/images/icons-png/arrow-u-black.png
rostful-0.2.1.dist-info/METADATA
rostful-0.2.1.dist-info/RECORD
rostful-0.2.1.dist-info/WHEEL
rostful-0.2.1.dist-info/entry_points.txt
rostful-0.2.1.dist-info/pbr.json
rostful-0.2.1.dist-info/top_level.txt
