Metadata-Version: 2.1
Name: rostful
Version: 0.2.1
Summary: REST API for ROS
Home-page: http://github.com/asmodehn/rostful
Author: AlexV
Author-email: asmodehn@gmail.com
License: BSD
Platform: UNKNOWN
Requires-Dist: Flask (>=0.10.1)
Requires-Dist: Flask-Cors (>=3.0.2)
Requires-Dist: Flask-Restful (>=0.3.4)
Requires-Dist: Flask-reverse-proxy
Requires-Dist: click (>=6.2.0)
Requires-Dist: webargs (>=1.3.4)
Requires-Dist: pyros (>=0.4.3)
Requires-Dist: tornado (<5.0,>=4.2.1)
Requires-Dist: simplejson
Requires-Dist: tblib (>=1.2)
